{
  "format_version": "1.0.0",
  "minecraft:block": {
    "description": {
      "identifier": "paladium:obsidian_poison"
    },
    "components": {
      "minecraft:material_instances": {
        "materials": {
          "*": {
            "texture": "obsidian_poison"
          }
        }
      },
      "minecraft:destructible_by_mining": {
        "hardness": 50,
        "tool_type": 3,
        "tool_tier": 5
      },
      "minecraft:destructible_by_explosion": {
        "value": 60000
      },
      "paladium:effect_block": {
        "target_only": false,
        "rayon_propagation": 7,
        "add_effect_on_break": true,
        "effects": [
          {
            "id": "poison",
            "power": 1,
            "duration": 160
          }
        ]
      }
    }
  }
}