{
  "format_version": "1.0.0",
  "minecraft:recipe_shaped": {
    "description": {
      "identifier": "paladium:unclaim_finder_orange"
    },
    "tags": [
      "palamachine"
    ],
    "pattern": [
      " A ",
      "B B",
      "B B"
    ],
    "key": {
      "A": [
        {
          "item": "paladium:unclaim_finder_green"
        }
      ],
      "B": [
        {
          "item": "paladium:findium"
        }
      ]
    },
    "result": {
      "item": "paladium:unclaim_finder_orange"
    }
  }
}